{
  "source_file": "www.sharda.ac.in_Best_Private_Engineering_Science_College_in_Noida_Sharda_University_raw_2025-08-10-18-29-10.txt",
  "structured_data": {
    "general_info": {
      "summary": "This link points to the School of Engineering and Basic Sciences at Sharda University. It is likely to contain information about the programs offered, faculty, research, and facilities within this academic division.",
      "raw_content": "Source: https://www.sharda.ac.in/schools/engineering-and-basic-science"
    }
  }
}